setup.py
saedeploy/__init__.py
saedeploy/saedeploy.py
saedeploy.egg-info/PKG-INFO
saedeploy.egg-info/SOURCES.txt
saedeploy.egg-info/dependency_links.txt
saedeploy.egg-info/entry_points.txt
saedeploy.egg-info/requires.txt
saedeploy.egg-info/top_level.txt