Metadata-Version: 1.0
Name: saedeploy
Version: 0.9
Summary: A handy command-line tool to deploy apps to Sina App Engine
Home-page: https://github.com/zhuzhuor/saedeploy
Author: Bo Zhu
Author-email: UNKNOWN
License: MIT
Platform: UNKNOWN
